tests/__init__.py
tests/test_client.py
tests/test_endpoints.py
tornapi/__init__.py
tornapi/client.py
tornapi/exceptions.py
tornapi/endpoints/__init__.py
tornapi/endpoints/torn.py
tornapi/endpoints/user.py
tornapi-0.2.0.dist-info/LICENSE
tornapi-0.2.0.dist-info/METADATA
tornapi-0.2.0.dist-info/WHEEL
tornapi-0.2.0.dist-info/top_level.txt
tornapi-0.2.0.dist-info/RECORD
