Metadata-Version: 2.1
Name: tornapi
Version: 0.2.0
Summary: A Python library for interacting with the Torn API
Home-page: https://github.com/nikkel/tornapi
Author: Ryan Clark
License: MIT
Classifier: Programming Language :: Python :: 3
Classifier: License :: OSI Approved :: MIT License
Classifier: Operating System :: OS Independent
Requires-Python: >=3.9
License-File: LICENSE
Requires-Dist: requests
